MANIFEST.in
README.md
requirements.txt
setup.py
wsgi_tracer/__init__.py
wsgi_tracer/apm.py
wsgi_tracer/filter.py
wsgi_tracer/logger.py
wsgi_tracer/mapper.py
wsgi_tracer/settings.py
wsgi_tracer/tracer.py
wsgi_tracer/utils.py
wsgi_tracer.egg-info/PKG-INFO
wsgi_tracer.egg-info/SOURCES.txt
wsgi_tracer.egg-info/dependency_links.txt
wsgi_tracer.egg-info/requires.txt
wsgi_tracer.egg-info/top_level.txt