Metadata-Version: 1.1
Name: wsgi-tracer
Version: 1.3
Summary: wsgi_tracer is a APM tracer helper for gunicorn
Home-page: UNKNOWN
Author: Ryan Kung
Author-email: ryankung@ieee.org
License: GPL
Platform: UNKNOWN
Classifier: Development Status :: 4 - Beta
Classifier: Environment :: Console
Classifier: Programming Language :: Python :: 3.5
Classifier: Operating System :: OS Independent
Classifier: Topic :: Software Development
Classifier: Topic :: Software Development :: Libraries :: Python Modules
